MANIFEST.in
README.rst
setup.cfg
setup.py
collective/__init__.py
collective.prettyphoto.egg-info/PKG-INFO
collective.prettyphoto.egg-info/SOURCES.txt
collective.prettyphoto.egg-info/dependency_links.txt
collective.prettyphoto.egg-info/entry_points.txt
collective.prettyphoto.egg-info/namespace_packages.txt
collective.prettyphoto.egg-info/not-zip-safe
collective.prettyphoto.egg-info/requires.txt
collective.prettyphoto.egg-info/top_level.txt
collective/prettyphoto/__init__.py
collective/prettyphoto/configure.zcml
collective/prettyphoto/exportimport.py
collective/prettyphoto/interfaces.py
collective/prettyphoto/migration.py
collective/prettyphoto/setuphandlers.py
collective/prettyphoto/skins.zcml
collective/prettyphoto/testing.py
collective/prettyphoto/testing.zcml
collective/prettyphoto/Extensions/Install.py
collective/prettyphoto/Extensions/__init__.py
collective/prettyphoto/browser/__init__.py
collective/prettyphoto/browser/configure.zcml
collective/prettyphoto/browser/view.py
collective/prettyphoto/browser/css/prettyPhoto.css
collective/prettyphoto/browser/images/dark_rounded/btnNext.png
collective/prettyphoto/browser/images/dark_rounded/btnPrevious.png
collective/prettyphoto/browser/images/dark_rounded/contentPattern.png
collective/prettyphoto/browser/images/dark_rounded/default_thumbnail.gif
collective/prettyphoto/browser/images/dark_rounded/loader.gif
collective/prettyphoto/browser/images/dark_rounded/sprite.png
collective/prettyphoto/browser/images/dark_square/btnNext.png
collective/prettyphoto/browser/images/dark_square/btnPrevious.png
collective/prettyphoto/browser/images/dark_square/contentPattern.png
collective/prettyphoto/browser/images/dark_square/default_thumbnail.gif
collective/prettyphoto/browser/images/dark_square/loader.gif
collective/prettyphoto/browser/images/dark_square/sprite.png
collective/prettyphoto/browser/images/default/default_thumb.png
collective/prettyphoto/browser/images/default/loader.gif
collective/prettyphoto/browser/images/default/sprite.png
collective/prettyphoto/browser/images/default/sprite_next.png
collective/prettyphoto/browser/images/default/sprite_prev.png
collective/prettyphoto/browser/images/default/sprite_x.png
collective/prettyphoto/browser/images/default/sprite_y.png
collective/prettyphoto/browser/images/facebook/btnNext.png
collective/prettyphoto/browser/images/facebook/btnPrevious.png
