Metadata-Version: 1.1
Name: collective.prettyphoto
Version: 0.6
Summary: prettyPhoto integration for Plone.
Home-page: https://github.com/collective/collective.prettyphoto
Author: Thomas Massmann
Author-email: thomas.massmann@inqbus.de
License: GPL
Keywords: Plone Lightbox jQuery
Platform: UNKNOWN
Classifier: Framework :: Plone :: 3.3
Classifier: Framework :: Plone :: 4.0
Classifier: Framework :: Plone :: 4.1
Classifier: Framework :: Plone :: 4.2
Classifier: Framework :: Plone :: 4.3
Classifier: Programming Language :: Python
